[{"name":"Teekkariravintolat","address":"Otakaari 24, Espoo","campus":"Otaniemi","open":"Mon-Fri 10:30-15:00","url":{"fi":"http://www.sodexo.fi/dipoli"},"location":{"lat":60.1847778,"lng":24.8309887}},{"name":"TUAS-talo","address":"Otaniementie 17, Espoo","campus":"Otaniemi","open":"Mon-Fri 10:30-14:00","url":{"fi":"http://www.amica.fi/TUAS","en":"http://www.amica.fi/en/TUAS"},"location":{"lat":60.1868196,"lng":24.8187598},"meals":{"fi":[["Yrttiöljymaustettuja jauhelihapyöryköitä (L, M), Pippurikastiketta (VL)","Keitettyjä perunoita (*, G, L, M)","Kasvis-vehnärisottoa (*, L, M)","Mozzarella-tomaattisalaattia ja paahdettua pestoleipää (*)","À la carte: Porsaanleike, paprikaa ja sipulia (L, M), Annanperunoita (G, L, M)","Kuningatarkiisseliä (G, L, M)"],["Chilimaustettua broileri-papupataa (*, G, L, M), Ruis-riisiä (*, L, M)","Quornia curry-kasviskastikkeessa (G, L, M), Ruis-riisiä (*, L, M)","Parsakaalisosekeittoa (*, G, VL)","À la carte: Kalkkunaleike (L, M), Tomaatti-vehnäsuurimolisäkettä (L, M)","Ananas-kermaviilikastiketta (G, L)","Omena-kauramurupaistosta (L, M), Vaniljakastiketta (G)"],["Savukinkkukastiketta (VL), Värikästä pennepastaa (L, M)","Jogurttista linssi-kasvismuhennosta (*, G, L), Ruis-riisiä (*, L, M)","Kylmäsavulohisalaattia (G, L)","À la carte: Grillattu broilerin fileepihvi  (G, L, M), Paprikariisiä (G, L, M)","Sahramikastiketta (G, L)","Mariannerahkaa (G, VL)"],["Kalkkunaa ja vihanneksia kookoskastikkeessa (*, G, L, M), Ruis-riisiä (*, L, M)","Kasvis-juustopataa (*, G, VL), Ruis-riisiä (*, L, M)","Bataattisosekeittoa (*, G, VL)","À la carte: Paistettua haukea (*, L, M), Keitettyjä perunoita (*, G, L, M)","Kananmuna-tillikastiketta (*, VL)","Hedelmiä sokeriliemessä (G, L, M), Kermavaahtoa (G, L)"],["Jauheliha-makaronipataa (*, L, M)","Pinaattiohukaisia (L), Keitettyjä perunoita (*, G, L, M), Puolukkasurvosta (G, L, M)","Kreikkalaista fetasalaattia (G, VL)","À la carte: Sitruunainen broilerinfilee (*, L), Seesamsiemenillä maustettuja perunoita (*, G, L, M)","Mokka-mandariinivaahtoa (G, L)"]],"en":[["Meatballs seasoned with herbs (L, M), Boiled potatoes (*, G, L, M), Mild pepper sauce (VL)","Vegetable and wheat groat risotto (*, L, M)","Tomato and mozzarella salad with toasted pesto bread (*)","À la carte: Pork schnitzel à la Puszta (L, M), Anna potatoes (G, L, M)","Blueberry and raspberry fool (G, L, M)"],["Chilli con carne, chicken stew (*, G, L, M), Rye-rice (*, L, M)","Quorn in curry & vegetable sauce (G, L, M), Rye-rice (*, L, M)","Pureed broccoli soup (*, G, VL)","À la carte: Breaded turkey escalope à la Amica (L, M), Tomato and wheat side dish (L, M)","Sour cream and pineapple sauce (G, L)","Apple and oatmeal crumb bake (L, M), Vanilla custard (G)"],["Smoked ham sauce (VL), Colourful penne pasta (L, M)","Lentil and vegetable stew with yoghurt (*, G, L), Rye-rice (*, L, M)","Salad with cold-smoked salmon (G, L)","À la carte: Grilled chicken patty (G, L, M), Rice with bell pepper (G, L, M)","Saffron sauce (G, L)","Marianne candy and curd dessert (G, VL)"],["Turkey and vegetables in coconut sauce (*, G, L, M), Rye-rice (*, L, M)","Cheese and vegetable stew (*, G, VL), Rye-rice (*, L, M)","Pureed sweet potato soup (*, G, VL)","À la carte: Fried pike (*, L, M), Boiled potatoes (*, G, L, M), Egg and dill sauce (*, VL)","Fruit compote (G, L, M), Whipped cream (G, L)"],["Minced meat and macaroni stew (*, L, M)","Spinach crêpes (L), Boiled potatoes (*, G, L, M), Lingonberry jam (G, L, M)","Greek-style Feta cheese salad (G, VL)","À la carte: Chicken fillet with lemon (*, L), Sesame potatoes (*, G, L, M)","Mocha and tangerine mousse (G, L)"]]}},{"name":"Alvari","address":"Otakaari 2, Espoo","campus":"Otaniemi","open":"Mon-Fri 10:30-14:00","url":{"fi":"http://www.amica.fi/alvari","en":"http://www.amica.fi/en/alvari"},"location":{"lat":60.1862055,"lng":24.8262297},"meals":{"fi":null,"en":null}},{"name":"Elissa","address":"Otakaari 2, Espoo","campus":"Otaniemi","open":"Mon-Fri 08:00-14:00","url":{"fi":"http://www.amica.fi/elissa"},"location":{"lat":60.1862055,"lng":24.8262297}},{"name":"Puu","address":"Tekniikantie 3, Espoo","campus":"Otaniemi","open":"Mon-Fri 10:30-13:30","url":{"fi":"http://www.amica.fi/Puu2"},"location":{"lat":60.1805857,"lng":24.8249123}},{"name":"Täffä","address":"Otakaari 22, Espoo","campus":"Otaniemi","open":"Mon-Thu 10:30-16:00, Fri 10:30-15:00","url":{"fi":"https://www.teknologforeningen.fi/index.php?option=com_content&view=article&id=277&Itemid=128&lang=fi","en":"https://www.teknologforeningen.fi/index.php?option=com_content&view=article&id=277&Itemid=128&lang=en"},"location":{"lat":60.1858857,"lng":24.83245},"meals":{"fi":[["Parsakaali-juusto täytetty kalarulla vl","Punajuuri-aurajuustokiusaus l g","Aurajuustosalaatti l","Kukkakaalikeitto g l","A la Carte: Täffänleike vl g",""],["Broilerin rintaleike, paprikakastike vl g","Ratatouille g l","Pekonisalaatti l g","Pinaattikeitto, 1/2 muna g l","A la Carte: Bratwurstkori, dijonmajoneesi l g",""],["Spaghetti bolognese l","Gorgonzolakastike l","Kotijuusto salaatti g vl","Kaalikeitto g l","A la Carte: Grillipihvi l g",""],["Pannupihvi, pekoni-sipulikastike","Kasvispihvit, omena-kermaviilikastike vl g","Lohi caesar vl","Kanakeitto l g","A la Carte: Sipulipihvi l g",""],["Sveitsinleike, perunamuhennos","Täytetyt paprikat g l","Kreikkalainen maalaissalaatti vl g","Tomaattinen jauhelihakeitto l g","A la Carte: Grillattu lohi, remuladekastike, lohkoperunat l g",""]],"en":[["Broccoli and cheese filled fish vl","Beetroot and aura cheese temptation l g","Aura cheese salad l","Cauliflower soup g l","A la Carte: Täffäs's schnitzel vl g",""],["Chicken breast with pepper sauce vl g","Ratatouille g l","Bacon salad l g","Spinach soup and 1/2 egg g l","A la Carte: Bratwurst basket, dijon mayonnaise l g",""],["Spaghetti bolognese l","Gorgonzolasauce l","Finnish fresh cheese salad g vl","Cabbage soup g l","A la Carte: Grilled steak l g",""],["Ground meat steak, bacon and onion sauce","Vegetable beefs with apple and sour cream sauce vl g","Salmon saesar vl","Chicken soup l g","A la Carte: Onion steak l g",""],["Swiss schnitzel, mashed potatoe","Filled peppers g l","Greek country salad vl g","Minced meat soup with tomatoes l g","A la Carte: Grilled salmon, remoulade sauce, potato wedges l g",""]]}},{"name":"Kvarkki","address":"Otakaari 3, Espoo","campus":"Otaniemi","open":"Mon-Fri 10:30-14:00","url":{"fi":"http://www.amica.fi/kvarkki","en":"http://www.amica.fi/en/kvarkki"},"location":{"lat":60.1883476,"lng":24.8294072},"meals":{"fi":[["Bolognesekastiketta (*, G, L, M), Luomutäysjyväspagettia (*, L, M)","Sitruunakuorrutettua seitiä (*, L, M), Keitettyjä perunoita (*, G, L, M), Tilli-kermaviilikastiketta (G, L)","Quornia tomaatti-kasviskastikkeessa (*, G, L, M), Luomutäysjyväspagettia (*, L, M)","Kasvissosekeittoa (*, G, VL)","Juustoista broileri-vihannessalaattia ja chili-kermaviilikastiketta (*, G, L)","Ruusunmarjajogurttia (G, L)"],["Broileria ja kasviksia hapanimeläkastikkeessa (*, G, L, M), Ruis-riisiä (*, L, M)","Lohimurekepihvejä (*, L, M), Keitettyjä perunoita (*, G, L, M), Ruohosipuli-kermaviilikastiketta (G, L)","Siskonmakkarakeittoa (G, L, M)","Kikherne-bataattipataa (*, G, L, M), Keitettyjä perunoita (*, G, L, M)","Katkarapusalaatti (*, G, L)","À la carte: Yrttimaustettua porsaanfileetä (*, G, L, M), Viherpippurikastiketta (VL)"," Viipaleperunoita (G, VL)","Mango-vaniljahyytelöä (G, L)"],["Rukiisia silakoita (*, VL), Perunasosetta (*, G, VL)","Palapaistia (*, VL), Keitettyjä perunoita (*, G, L, M)","Soija-kasviskiusausta (*, G, VL)","Kasvisminestronea (*, L, M)","Kreikkalaista fetasalaattia (G, VL)","Omenapiirakkaa,Vaniljakastiketta (G)"],["Broileri-hedelmäkastiketta (*, VL), Luomutäysjyväkierrepastaa (*, L, M)","Jauheliha-paprikamureketta (L, M), Keitettyjä perunoita (*, G, L, M), Sipulikastiketta (*, VL)","Juustokuorrutettua kasvisgratiinia (*, VL)","Linssisosekeittoa (*, G, VL)","Savukirjolohisalaattia ja kermaviilikastiketta (*, G, L)","À la carte: Wieninleike (L, M), Perunasosetta (*, G, VL)","Marjarahkaa (G, L)"],["Kylmäsavulohi-juustokastiketta (VL), Värikästä pennepastaa (L, M)","Papu-vihannespastaa (*, L, M)","Luomutofu-kasviskeittoa (*, G, L, M)","Mozzarella-tomaattisalaattia ja paahdettua pestoleipää (*)","Naudanlihapannupizzaa (L)","Cappuccinovaahtoa (G, VL)"]],"en":[["Bolognese sauce (*, G, L, M), Whole grain organic spaghetti (*, L, M)","Lemon-gratinated saithe (*, L, M), Boiled potatoes (*, G, L, M), Sour cream sauce with dill (G, L)","Quorn in tomato & vegetable sauce (*, G, L, M), Whole grain organic spaghetti (*, L, M)","Pureed vegetable soup (*, G, VL)","Chicken and vegetable salad with cheese and chilli and sour cream dressing (*, G, L)","Rosehip yoghurt (G, L)"],["Chicken and vegetables in sweet and sour sauce (*, G, L, M), Rye-rice (*, L, M)","Fish loaf patties (*, L, M), Boiled potatoes (*, G, L, M), Sour cream sauce with chives (G, L)","Pork sausage soup (G, L, M)","Chickpea and sweet potato casserole (*, G, L, M), Boiled potatoes (*, G, L, M)","Shrimp salad (*, G, L)","À la carte: Pork fillet with herbs (*, G, L, M), Scalloped potatoes (G, VL)"," Green pepper sauce (VL)","Mango and vanilla jelly (G, L)"],["Baltic herrings with rye (*, VL), Mashed potatoes (*, G, VL)","Stroganoff (*, VL), Boiled potatoes (*, G, L, M)","Spicy soy casserole (*, G, VL)","Vegetable minestrone soup (*, L, M)","Greek-style Feta cheese salad (G, VL)","Apple pie,Vanilla custard (G)"],["Chicken and fruit sauce (*, VL), Whole grain organic pasta (*, L, M)","Meatloaf seasoned with bell pepper (L, M), Boiled potatoes (*, G, L, M), Onion sauce (*, VL)","Vegetables au gratin (*, VL)","Pureed lentil soup (*, G, VL)","Smoked rainbow trout salad and sour cream dressing (*, G, L)","À la carte: Wiener Schnitzel (L, M), Mashed potatoes (*, G, VL)","Berry curd dessert (G, L)"],["Smoked salmon and cream cheese sauce (VL), Colourful penne pasta (L, M)","Vegetable pasta with beans (*, L, M)","Organic tofu and vegetable soup (*, G, L, M)","Tomato and mozzarella salad with toasted pesto bread (*)","Beef pan pizza (L)","Cappuccino mousse (G, VL)"]]}},{"name":"Silinteri","address":"Otakaari 1 D, Espoo","campus":"Otaniemi","open":"Mon-Fri 11:40-13:00","url":{"fi":"http://www.amica.fi/silinteri"},"location":{"lat":60.1869326,"lng":24.8272611}},{"name":"Cantina","address":"Otakaari 24, Espoo","campus":"Otaniemi","open":"Mon-Thu 11:00-22:30, Fri 11:00-22:30, Sat 11:00-17:00","url":{"fi":"http://www.sodexo.fi/cantina"},"location":{"lat":60.1847778,"lng":24.8309887}},{"name":"Laurea Otaniemi","address":"Metsänpojankuja 3, Espoo","campus":"Otaniemi","open":"Mon-Thu 11:00-13:15, Fri 11:00-13:00","url":{"fi":"http://www.amica.fi/laureaotaniemi"},"location":{"lat":60.1858113,"lng":24.8054439}},{"name":"Rafla","address":"Runeberginkatu 14, Helsinki","campus":"Töölö","open":"Mon-Fri 10:30-16:15","url":{"fi":"http://www.amica.fi/rafla","en":"http://www.amica.fi/en/rafla"},"location":{"lat":60.1709066,"lng":24.9236468},"meals":{"fi":[["Tomattista jauheliha-paprikakastiketta (*, L, M), Keitettyjä persiljaperunoita (*, G, L, M)","Pähkinäistä kasvis-vehnärisottoa (L, M)","Kotijuusto-vihannessalaattia ja pestoleipää (*)","Porsaan grillipihvi (G, L, M), Paahdettuja rosamunda-perunoita (G, L, M), Punaviinikastiketta (*, VL)","Mansikkariisiä (G, L)"],["Naudanliha-smetanakastiketta (*, L), Ruis-riisiä (*, L, M)","Bataatti-maissipihvejä (G, L, M), Linssi-kasvispyöryköitä (G, L, M), Ruis-riisiä (*, L, M), Basilika-kermaviilikastiketta (G, L), Raejuusto-vihannessalaattia ja pestokastiketta (*, G)","Paistettua kirjolohta (L, M), Muhennettua perunaaSitruunalohko (G, L, M)","Mustikkavispipuuroa (L, M)"],["Makkara-perunapannua ja paistettu kananmuna (*, G, L, M)","Luomutofu-kasviscurrya (*, G, L, M), Täysjyväohraa (*, L, M)","Juuressosekeittoa (*, G, VL)","Savustettua kirjolohta, peruna-vihannessalaattia ja kermaviilikastiketta (*, G, L)","Appelsiini-rahkahyytelöä (G, L)"],["Meksikolaista jauheliha-kasvisrisottoa (*, G, L, M)","Tomaatti-vuohenjuustokastiketta (*, G), Luomutäysjyväpennepastaa (*, L, M)","Kasvis-jauhelihasalaattia ja tortillachipsejä (*, G, L)","Broilerin rintaleike smetana-tomaattikastikkeessa (*, G, L), Paahdettua perunaa (G, L, M), Sipuli-papuja (G, L, M)","Hedelmäsalaattia (G, L, M)"],["Rapeita kalapaloja (*, L, M), Perunasosetta (*, G, VL), Sinappirelish-kermaviilikastiketta (G, L)","Chili con vege (*, G, L, M), Ruis-riisiä (*, L, M)","Katkarapusalaatti (*, G, L)","Pippurinen porsaanfilepihvi (*, G, L, M), Lohkoperunoita (G, L, M), Persiljavoita (G, VL)","Aprikoosirahkaa (G, L)"]],"en":[["Minced meat goulash sauce (*, L, M), Boiled potatoes with parsley (*, G, L, M)","Spicy vegetable and wheat ragout (L, M)","Homemade cheese and vegetable salad with pesto bread (*)","Grilled pork steak (G, L, M), Roasted rosamunda potatoes (G, L, M), Red wine sauce (*, VL)","trawberry rice (G, L)"],["Beef in sour cream sauce (*, L), Rye-rice (*, L, M)","Sweet potato and corn patties (G, L, M), Vegetable rissoles (G, L, M), Rye-rice (*, L, M), Sour cream sauce with basil (G, L)","Cottage cheese salad (*, G)","Fried rainbow trout (L, M), Mashed potatoesLemon (G, L, M)","Whipped blueberry porridge (L, M)"],["Sausage and potato casserole and fried egg (*, G, L, M)","Vegetable curry with organic tofu (*, G, L, M), Wholemeal barley (*, L, M)","Pureed root vegetable soup (*, G, VL)","Smoked rainbow trout, potato and vegetable salad and sour cream dressing (*, G, L)","Orange curd jelly (G, L)"],["Mexican-style minced meat risotto (*, G, L, M)","Tomato and goat cheese sauce (*, G), Whole grain organic pasta (*, L, M)","Vegetable and minced meat salad with tortilla chips (*, G, L)","Georgian-style chicken breast (*, G, L), Roasted potatoes (G, L, M), Beans with onion (G, L, M)","Fruit salad (G, L, M)"],["Crispy fish pieces (*, L, M), Mashed potatoes (*, G, VL), Mustard relish sauce (G, L)","Vegetarian chili (*, G, L, M), Rye-rice (*, L, M)","Shrimp salad (*, G, L)","Pork fillet steak with pepper (*, G, L, M), Potato wedges (G, L, M), Parsley butter à la Amica (G, VL)","Apricot curd dessert (G, L)"]]}},{"name":"Chydenia","address":"Runeberginkatu 22, Helsinki","campus":"Töölö","open":"Mon-Thu 11:00-14:30, Fri 11:00-14:00","url":{"fi":"http://www.amica.fi/chydenia","en":"http://www.amica.fi/en/chydenia"},"location":{"lat":60.1735677,"lng":24.9222099}},{"name":"Hanken","address":"Arkadiankatu 22, Helsinki","campus":"Töölö","open":"Mon-Fri 11:00-15:00","url":{"fi":"http://www.amica.fi/hanken","en":"http://www.amica.fi/en/hanken"},"location":{"lat":60.1712571,"lng":24.9243845}},{"name":"Sibelius-Akatemia / R-Talo","address":"Pohjoinen Rautatiekatu 9, Helsinki","campus":"Töölö","open":"Mon-Thu 10:30-15:00, Fri 10:30-14:30","url":{"fi":"http://www.amica.fi/r-talo","en":"http://www.amica.fi/en/r-talo"},"location":{"lat":60.1715396,"lng":24.9325754},"meals":{"fi":[["Tomattista jauheliha-paprikakastiketta (L,M,*)","Keitettyjä persiljaperunoita (L,G,M,*)","Hinta: 2,60/4,80/5,00/6,80"],["Pähkinäistä kasvis-vehnärisottoa (L,M)","Hinta: 2,60/4,80/5,00/6,80"],["Kalaa katkarapukastikkeessa (VL,*)","Keitettyjä perunoita (L,G,M,*)","Hinta: 2,60/4,80/5,00/6,80"],["Linssi-kasvispyöryköitä (L,G,M)","Basilika-kermaviilikastiketta (L,G)","Keitettyjä perunoita (L,G,M,*)","Hinta: 2,60/4,80/5,00/6,80"],["Juustoista broileri-paprikakastiketta (G,VL,*)","Luomutäysjyväkierrepastaa (L,M,*)","Hinta: 2,60/4,80/5,00/6,80"],["Luomutofu-kasviscurrya (L,G,M,*)","Täysjyväohraa (L,M,*)","Hinta: 2,60/4,80/5,00/6,80"],["Broilerin rintaleike smetana-tomaattikastikkeessa (L,G,*)","Paahdettua perunaa (L,G,M)","Hinta: 4,50/6,50/6,90/8,25"],["Hedelmäsalaattia (L,G,M)","Kermavaahtoa (L,G)","Hinta: 1,20"],["Kebabliha-kasviskastiketta (L,G,M,*)","Ruis-riisiä (L,M,*)","Hinta: 2,60/4,80/5,00/6,80"],["Chili con vege (L,G,M,*)","Ruis-riisiä (L,M,*)","Hinta: 2,60/4,80/5,00/6,80"]],"en":[["Minced meat goulash sauce (L,M,*)","Boiled potatoes with parsley (L,G,M,*)","Price: 2,60/4,80/5,00/6,80"],["Spicy vegetable and wheat ragout (L,M)","Price: 2,60/4,80/5,00/6,80"],["Saithe with shrimp (VL,*)","Boiled potatoes (L,G,M,*)","Price: 2,60/4,80/5,00/6,80"],["Vegetable rissoles (L,G,M)","Sour cream sauce with basil (L,G)","Boiled potatoes (L,G,M,*)","Price: 2,60/4,80/5,00/6,80"],["Chicken and cheese sauce (G,VL,*)","Whole grain organic pasta (L,M,*)","Price: 2,60/4,80/5,00/6,80"],["Vegetable curry with organic tofu (L,G,M,*)","Wholemeal barley (L,M,*)","Price: 2,60/4,80/5,00/6,80"],["Georgian-style chicken breast (L,G,*)","Roasted potatoes (L,G,M)","Price: 4,50/6,50/6,90/8,25"],["Fruit salad (L,G,M)","Whipped cream (L,G)","Price: 1,20"],["Kebab and vegetable sauce (L,G,M,*)","Rye-rice (L,M,*)","Price: 2,60/4,80/5,00/6,80"],["Vegetarian chili (L,G,M,*)","Rye-rice (L,M,*)","Price: 2,60/4,80/5,00/6,80"]]}},{"name":"Cafe da Capo","address":"Töölönkatu 28, Helsinki","campus":"Töölö","open":"Mon-Thu 10:30-16:00, Fri 10:30-15:00","url":{"fi":"http://www.amica.fi/cafedacapo","en":"http://www.amica.fi/en/cafedacapo"},"location":{"lat":60.1785198,"lng":24.9266378}},{"name":"HYSn Osakuntabaari","address":"Urho Kekkosen katu 4-6 D, Helsinki","campus":"Töölö","open":"Mon-Thu 11:00-15:30, Fri 11:00-15:00","url":{"fi":"http://www.hys.net/opiskelijapalvelut/osakuntabaari/ruokalista"},"location":{"lat":60.1687878,"lng":24.9343696},"meals":{"fi":null,"en":[]}},{"name":"Musiikkitalon Ravintola","address":"Mannerheimintie 13 A, Helsinki","campus":"Töölö","open":"Mon-Fri 11:00-15:00","url":{"fi":"http://www.tapahtumaravintolat.fi/musiikkitalo/Ravintolapalvelut/fi_FI/Ravintola/"},"location":{"lat":60.1731905,"lng":24.9344303}},{"name":"Kipsari","address":"Hämeentie 135 E, Helsinki","campus":"Arabia","open":"Mon-Fri 08:00-19:00","url":{"fi":"https://www.facebook.com/kipsari"},"location":{"lat":60.2087625,"lng":24.9756101}},{"name":"Meccala","address":"Hämeentie 135 C, Helsinki","campus":"Arabia","open":"Mon-Thu 10:30-14:15, Fri 10:30-14:00","url":{"fi":"http://www.amica.fi/meccala","en":"http://www.amica.fi/en/meccala"},"location":{"lat":60.2087625,"lng":24.9756101}},{"name":"Ravintola Arabianranta","address":"Hämeentie 135 A, Helsinki","campus":"Arabia","open":"Mon-Fri 10:30-13:30","url":{"fi":"http://www.compass-group.fi/ravintolat/Helsinki/ravintola-arabianranta/Lounaslista/"},"location":{"lat":60.2087625,"lng":24.9756101},"meals":{"fi":[["Juustosalaattia G ","*Tulisempaa tomaattikeittoa L,G ","*Jauhelihabolognesea ja pastaa L "," *Kasviskääryleitä ja porkkanatzatzikia L ","Paistettua kalaa,jokirapukermakastiketta ja palsternakka-perunapyrettä "," Valikoima jälkiruokia"],["Nizzansalaattia M,L,G ","*Nakki-vihanneskeittoa L,G ","*Parsakaali-juustokalaa ja tilliperunoita ","*Juustoista kasvisgratiinia ","Nautaa ja herkkusieniä pippurikastikkeessa, maalaislohkoperunoita L,G L "," Valikoima jälkiruokia "],["Salaattia pippurimarinoidusta porsaasta  M,L, G ","*Tuorejuustolla maustettua kesäkurpitsakeittoa G ","*Riistapyöryköitä ja tummaa punasipulikastiketta L ","*Kasvis-soijatäytteisiä paprikoita G ","Kalkkunan filettä, punaviinikastiketta ja papu-pekonipaistosta L ","Valikoima jälkiruokia"],["Kana-Ceasar  salaattia G,L,M ","*Parksakeittoa L,G ","*Tonnikalalasagnettea ","*Kasvis-tuoreyrttikastiketta ja luomuriisiä L,G ","Possunpihviä back&white ja rosmariinipaahdettuja juureksia M,L,G ","Valikoima jälkiruokia "],["*Savuporo-juustokeittoa G ","*Kasvisfajitaksia M,L "," *Possun stroganoff ja persiljaperunoita  M,L,G "," Paahdettua kanaa, grillattua vuohenjuustoa, viikunahilloa ja villiriisiä G ","Valikoima jälkiruokia ","Ravintola suljettu 01.07.-04.08.2013.","L = lactose free "]],"en":[[" Cheese Salad G"," Hot tomato soup L,G"," Ground meat bolognese and pasta L"," Vegetarian rolls and tzatziki with carrots L"," Fried fish, European crayfish sauce with potato and parsnip pure","Selection of desserts"],[" Salad Nizza L, M,G"," Frankfurter and vegetable soup L,G"," Owen baked fish with broccoli and cheese, steamed potatoes with dill "," Cheese gratinated vegetables","Beef and mushrooms in pepper sauce with owen baked potatoes L,G"," Selection of desserts"],["  Pepper spiced pork salad M,L, G"," Zuccini Soup with fresh cheese G","Game rolls and dark red onion sauce L L"," Sweet peppers stuffed with vegetables and soy G"," Turkey fillet, red onion sauce with bean and bacon bale L","Selection of desserts"],["  Chicken Ceasar salad G,L,M"," Asparagus Soup L,G","Tuna fish lasagnette"," Vegetable sauce with fresh herbs and steamed organic rice  L,G"," Pork escalope balck&white with rosemary roasted root vegetables M,L,G"," Selection of desserts"],[" Smoked reindeer soup with cheese G"," Vegetable Fajitas M,L"," Pork stroganoff and steamed potatoe swith parsley M,L,G"," Owen roasted chiken fillet, grilled goat cheese, fig jam and steamed wild rice G"," Selection of desserts","Ravintola suljettu 01.07.-04.08.2013."," laktoositon"]]}},{"name":"Unicafe Chemicum","address":"A.I. Virtasen aukio 1, Helsinki","campus":"Kumpula","open":"Mon-Thu 10:30-15:30, Fri 10:30-15:00","url":{"fi":"http://www.hyyravintolat.fi/rss/fin/10/","en":"http://www.hyyravintolat.fi/rss/eng/10/"},"location":{"lat":60.2060455,"lng":24.9634222},"meals":{"fi":[["Nakkikastiketta (l,m,v)","Uunikalaa ([S],g,l)","Falafel-pyörykät, tzatziki (k,l,se,v)","Hedelmäinen kalkkunasalaatti ([S],l)","Rahkapiirakkaa (k,l)","Olemme avoinna klo 8.00-14.00! "],["Viinitarhan lohta ([S],g,l)","Jauhelihalasagnettea ([S],v,vl)","Soijaa thaicurrykastikkeessa ([S],g,k,l,m,so,v,ve)","Kinkkusalaatti ([S],g,l,m)","Olemme avoinna klo 8.00-14.00! "],["Stroganoffia ([S],l)","Seilorin turskaa, tilli-kermaviilikastiketta ([S],l)","Tofu-kookoscurrya (g,k,l,m,so,v,ve)","Cheddarsalaatti (k,l)","Porkkanasosekeittoa (g,k,pä)","Olemme avoinna klo 8.00-14.00! "],["Kalkkuna-herkkusienipataa ([S],g,vl)","Seitä hollandaisekastikkeessa ([S],g)","Pinaattiohukaisia, puolukkahilloa ([S],k,l)","Nizzansalaatti (g,l,m)","Olemme avoinna klo 8.00-14.00! "],["Kaprislohta (l)","Kebabkastiketta ([S],g,l,m,so,v)","Soijabolognaisea ([S],g,k,l,m,so,v,ve)","Parmesansalaatti (k,l)","Olemme avoinna klo 8.00-14.00! "],["HYVÄÄ VIIKONLOPPUA ! "],["HYVÄÄ VIIKONLOPPUA ! "]],"en":[["Frankfurter sauce (l,m,v)","Baked fish ([S],g,l)","Falafel balls, tzatziki (k,l,se,v)","Fruity turkey salad ([S],l)"," (k,l)"," "],["The Vineyard's salmon ([S],g,l)","Minced meat lasagnette ([S],v,vl)","Soya in Thai curry sauce ([S],g,k,l,m,so,v,ve)","Ham salad ([S],g,l,m)"," "],["Stroganoff ([S],l)","Sailors cod, dil-sour cream sauce ([S],l)","Tofu coconut curry (g,k,l,m,so,v,ve)","Cheddar salad (k,l)","Carrot purée soup (g,k,pä)"," "],["Turkey-mushroom pot ([S],g,vl)","Pollock in sauce hollandaise ([S],g)","Spinach crepes ([S],k,l)","Salad á la Nicoise (g,l,m)"," "],["Salmon in capers sauce (l)","Kebab sauce ([S],g,l,m,so,v)","Soyabolognaise ([S],g,k,l,m,so,v,ve)","Parmesan salad (k,l)"," "],[" "],[" "]]}},{"name":"Unicafe Exactum","address":"Gustaf Hällströmin katu 2 B, Helsinki","campus":"Kumpula","open":"Mon-Fri 11:00-14:30","url":{"fi":"http://www.hyyravintolat.fi/rss/fin/11/","en":"http://www.hyyravintolat.fi/rss/eng/11/"},"location":{"lat":60.2049747,"lng":24.9634712},"meals":{"fi":[],"en":[]}},{"name":"Unicafe Metsätalo","address":"Fabianinkatu 39, Helsinki","campus":"Keskusta","open":"Mon-Thu 10:30-16:00, Fri 10:30-15:00","url":{"fi":"http://www.hyyravintolat.fi/rss/fin/1/","en":"http://www.hyyravintolat.fi/rss/eng/1/"},"location":{"lat":60.1722975,"lng":24.949109},"meals":{"fi":[],"en":[]}},{"name":"Unicafe Olivia","address":"Siltavuorenpenger 5 A, Helsinki","campus":"Keskusta","open":"Mon-Thu 10:30-16:00, Fri 10:30-15:30","url":{"fi":"http://www.hyyravintolat.fi/rss/fin/2/","en":"http://www.hyyravintolat.fi/rss/eng/2/"},"location":{"lat":60.1751035,"lng":24.9533853},"meals":{"fi":[],"en":[]}},{"name":"Unicafe Porthania","address":"Yliopistonkatu 3, Helsinki","campus":"Keskusta","open":"Mon-Thu 10:30-16:30, Fri 10:30-16:00","url":{"fi":"http://www.hyyravintolat.fi/rss/fin/3/","en":"http://www.hyyravintolat.fi/rss/eng/3/"},"location":{"lat":60.1699536,"lng":24.9484354},"meals":{"fi":[["Lohikiusausta ([S],g,l)","Porsaan palapaistia ([S],l,m)","Kasvis-papukroketit, ruohosipuli-jogurttikastiketta (g,k,l,so,v)","Kreikkalainen salaatti (g,k,v,vl)","Tomaattikeittoa, raejuustoa (k,l)"],["Jauhelihabolognaisea, juustoraastetta ([S],g,l,pä,v)","Savukalakastike ([S],g,vl)","Pinaattikuorrutettua tofua ([S],k,l,m,pä,so,ve)","Broileri-waldorfinsalaatti ([S],g,l,pä,se)"],["Porsaanleike, pippurikastiketta (l)","Broileriwrap (l,so,v)","Aurajuustosilakoita ([S],g,l)","Soija-kasvispannua ([S],g,k,l,m,so,ve)","Makrillisalaatti ([S],g,l,m)"],["Mantelikuorrutettua seitä ([S],g,pä,vl)","Kikhernenuggetit, soijajogurttidippiä (k,l,m,so,v,ve)","Lihapullapannua (g,v)","Vuohenjuusto-pinjansiemensalaatti (g,k,pä)","Porkkanasosekeittoa (g,k,pä)"],["Lohta italialaisittain (g,l)","Jauhelihakebakot, paprikakastiketta (l,so,v)","Linssiwrap ([S],k,l,m,so,v,ve)","Tonnikalasalaatti ([S],g,l,m)"]],"en":[["Salmon temptation ([S],g,l)","Pork stew ([S],l,m)","Vegetable croquettes with beans, shallot yogurth sauce (g,k,l,so,v)","Greek salad (g,k,v,vl)","Tomato soup, cottage cheese (k,l)"],["Bolognaise with minced meat, grated cheese ([S],g,l,pä,v)"," ([S],g,vl)","Spinach covered tofu ([S],k,l,m,pä,so,ve)","Chicken Waldorfs salad ([S],g,l,pä,se)"],[" (l)","Chicken wrap (l,so,v)","Herring with blue cheese ([S],g,l)","Soya and vegetable pan ([S],g,k,l,m,so,ve)","Mackerel salad ([S],g,l,m)"],["Black cod amandine ([S],g,pä,vl)","Chickpea nuggets, soy yoghourt dip (k,l,m,so,v,ve)","Hodge podge with meat balls (g,v)","Salad with goat cheese and pine kernel (g,k,pä)","Carrot purée soup (g,k,pä)"],[" (g,l)","Minced meat sticks with sweet pepper sauce (l,so,v)"," ([S],k,l,m,so,v,ve)","Tuna salad ([S],g,l,m)"]]}},{"name":"Unicafe Päärakennus","address":"Fabianinkatu 33, Helsinki","campus":"Keskusta","open":"Mon-Fri 10:30-16:30","url":{"fi":"http://www.hyyravintolat.fi/rss/fin/4/","en":"http://www.hyyravintolat.fi/rss/eng/4/"},"location":{"lat":60.16944179999999,"lng":24.9494575},"meals":{"fi":[],"en":[]}},{"name":"Unicafe Rotunda","address":"Unioninkatu 36, Helsinki","campus":"Keskusta","open":"Mon-Fri 11:00-13:30","url":{"fi":"http://www.hyyravintolat.fi/rss/fin/5/","en":"http://www.hyyravintolat.fi/rss/eng/5/"},"location":{"lat":60.170351,"lng":24.9506851},"meals":{"fi":[],"en":[]}},{"name":"Unicafe Soc&Kom","address":"Yrjö-Koskisen katu 3, Helsinki","campus":"Keskusta","open":"Mon-Fri 11:00-14:30","url":{"fi":"http://www.hyyravintolat.fi/rss/fin/15/","en":"http://www.hyyravintolat.fi/rss/eng/15/"},"location":{"lat":60.1730803,"lng":24.9525119},"meals":{"fi":[],"en":[]}},{"name":"Unicafe Topelias","address":"Unioninkatu 38, Helsinki","campus":"Keskusta","open":"Mon-Thu 11:00-14:30, Fri 11:00-14:00","url":{"fi":"http://www.hyyravintolat.fi/rss/fin/6/","en":"http://www.hyyravintolat.fi/rss/eng/6/"},"location":{"lat":60.17186450000001,"lng":24.9504841},"meals":{"fi":[],"en":[]}},{"name":"Unicafe Valtiotiede","address":"Unioninkatu 37, Helsinki","campus":"Keskusta","open":"Mon-Fri 11:00-14:00","url":{"fi":"http://www.hyyravintolat.fi/rss/fin/7/","en":"http://www.hyyravintolat.fi/rss/eng/7/"},"location":{"lat":60.173379,"lng":24.9506235},"meals":{"fi":[],"en":[]}},{"name":"Unicafe Ylioppilasaukio","address":"Mannerheimintie 3 B, Helsinki","campus":"Keskusta","open":"Mon-Fri 11:00-19:00, Sat 11:00-18:00","url":{"fi":"http://www.hyyravintolat.fi/rss/fin/8/","en":"http://www.hyyravintolat.fi/rss/eng/8/"},"location":{"lat":60.1693166,"lng":24.9408102},"meals":{"fi":[["Mango-seesamikalaa (g,l,m,so,v)","Uunimakkara (g,l,v)","Tonnikala-katkarapukastiketta ([S],vl)","Kasvispilahvia,  tomaattikastiketta ([S],k,l,m,v,ve)","Itämaista kanakeittoa ([S],g,l,m,se,so,v)","Lounassalaatti ","Tomaattista makkarakeittoa (g,l,m)","Mansikkarahka (g,l)","Kesäaika: ravintola suljetaan kl 17.00 "],["Rapeaa uunibroileria (l,v)","Basilikahärkää ([S],l)","Lohimurekepihvit, sitruuna-kermaviilikastiketta (l)","Soijapyörykät chilitomaattikastikkeessa ([S],g,k,l,m,pä,so,v,ve)","Jauheliha-kesäkurpitsakeittoa ([S],g,l,m)","Lounassalaatti ","Banaanipaistos (l)","Kesäaika: ravintola suljetaan kl 17.00 "],["Porsaanleike, rosépippurikastiketta (l,v)","Lihapyöryköitä, ruskeaa kastiketta (l,so,v)","Pinaattinen uunikala (l)","Bataatti-papuhöystöä ([S],g,k,l,m,v,ve)","Siskonmakkarakeittoa ([S],g,l,m)","Lounassalaatti ","Appelsiinikiisseli (g,l)","Kesäaika: ravintola suljetaan kl 17.00 "],["Tomaattikuorutteinenlohi, basilika-tomaattikastiketta ([S],g,vl)","Chili-kookoskanaa ([S],g,l,m,se,so,v)","Silakkapihvejä, kermaviili-tillikastiketta ([S],l)","Tofu-perunalaatikkoa ([S],k,l,m,so,v,ve)","Katkarapu-nuudelikeittoa ([S],l,m,v)","Lounassalaatti ","Hedelmälassi (g,l)","Kesäaika: ravintola suljetaan kl 17.00 "],["Cheddar-täytteinen kalarulla, ruohosipulikastiketta ([S],v)","Jauhelihakastiketta, juustoraastetta ([S],l,v)","Merellinen ratatouille ([S],g,l,m)","Vihannespihvit, papusalsaa ([S],g,k,l,m,se,v,ve)","Lihakeittoa ([S],g,l,m)","Lounassalaatti ","Marjahyve (l)","Kesäaika: ravintola suljetaan kl 17.00 "]],"en":[["Fish with mango and sesame (g,l,m,so,v)","Baked sausage (g,l,v)","Tuna-shrimp sauce ([S],vl)","Vegetable pilaff with tomato sauce ([S],k,l,m,v,ve)","Oriental chicken soup ([S],g,l,m,se,so,v)","Lunch salad ","Tomato sausage soup (g,l,m)","Strawberry quark (g,l)","Summer time: the restaurant is closed at 17.00 "],["Crispy baked chicken (l,v)","Meat stew with basil ([S],l)","Salmon loaf, lemon-sour cream sauce (l)","Soya balls in chili-tomato sauce ([S],g,k,l,m,pä,so,v,ve)","Minced meat-zucchini soup ([S],g,l,m)","Lunch salad ","Baked banana dessert (l)","Summer time: the restaurant is closed at 17.00 "],["Pork schnitzel, pink pepper sauce (l,v)","Meatballs with gravy (l,so,v)","Baked fish with spinach (l)","Sweet potato-bean sauté ([S],g,k,l,m,v,ve)","Sausage soup ([S],g,l,m)","Lunch salad ","Orange kissel (g,l)","Summer time: the restaurant is closed at 17.00 "],["Tomato oven-browned salmon,  basil-tomato sauce ([S],g,vl)","Chicken, chili and coconut ([S],g,l,m,se,so,v)","Herring, dill-sour cream sauce ([S],l)","Tofu and potato casserole ([S],k,l,m,so,v,ve)","Shrimp noodle soup ([S],l,m,v)","Lunch salad ","Fruit lassi (g,l)","Summer time: the restaurant is closed at 17.00 "],["Cheddar stuffed fish roll with shallot sauce ([S],v)","Minced meat sauce, grated cheese ([S],l,v)","Ratatouille Fruit de Mer ([S],g,l,m)","Vegetablesteaks, bean salsa ([S],g,k,l,m,se,v,ve)","Meat soup ([S],g,l,m)","Lunch salad ","Berry dessert (l)","Summer time: the restaurant is closed at 17.00 "]]}},{"name":"Kasvisbaari","address":"Kaikukatu 4 B, Helsinki","campus":"Kallio","open":"Mon-Fri 11:00-16:00","url":{"fi":"http://www.kasvisbaari.fi/menu.php"},"location":{"lat":60.1830135,"lng":24.9591233},"meals":{"fi":[[null],[null],[null],[null],[null]],"en":[[null],[null],[null],[null],[null]]}},{"name":"Unicafe Kookos","address":"Haapaniemenkatu 6, Helsinki","campus":"Kallio","open":"Mon-Thu 11:00-17:00, Fri 11:00-15:00","url":{"fi":"http://www.hyyravintolat.fi/rss/fin/16/","en":"http://www.hyyravintolat.fi/rss/eng/16/"},"location":{"lat":60.1811256,"lng":24.9587522},"meals":{"fi":[],"en":[]}},{"name":"Unicafe Biokeskus","address":"Viikinkaari 9, Helsinki","campus":"Viikki","open":"Mon-Fri 10:30-15:00","url":{"fi":"http://www.hyyravintolat.fi/rss/fin/18/","en":"http://www.hyyravintolat.fi/rss/eng/18/"},"location":{"lat":60.2269484,"lng":25.0139846},"meals":{"fi":[["Mango-seesamikalaa (g,l,m,so,v)","Uunimakkara (g,l,v)","Kasvispilahvia,  tomaattikastiketta ([S],k,l,m,v,ve)","Tonnikala-katkarapukastiketta ([S],vl)","Kreikkalainen salaatti (g,k,v,vl)","Banaanirahka (g,k,l)"],["Basilikahärkää ([S],l)","Lohimurekepihvit, sitruuna-kermaviilikastiketta (l)","Soijapyörykät chilitomaattikastikkeessa ([S],g,k,l,m,pä,so,v,ve)","Makrillisalaatti ([S],g,l,m)","Purjo-perunasosekeittoa (g,k,l)"],["Lihapyöryköitä, ruskeaa kastiketta (l,so,v)","Pinaattinen uunikala (l)","Bataatti-papuhöystöä ([S],g,k,l,m,v,ve)","Vuohenjuustosalaattia (g,k,l,v)"],["Silakkapihvejä, kermaviili-tillikastiketta ([S],l)","Tofu-perunalaatikkoa ([S],k,l,m,so,v,ve)","Chili-kookoskanaa ([S],g,l,m,se,so,v)","Savukala-parsasalaattia ([S],g,l,m)","Vuohenjuustokeittoahedelmä (g,k,l,v)"],["Jauhelihakastiketta, juustoraastetta ([S],l,v)","Vihannespihvit, papusalsaa ([S],g,k,l,m,se,v,ve)","Merellinen ratatouille ([S],g,l,m)","Lisäkkeenä pastaa "]],"en":[["Fish with mango and sesame (g,l,m,so,v)","Baked sausage (g,l,v)","Vegetable pilaff with tomato sauce ([S],k,l,m,v,ve)","Tuna-shrimp sauce ([S],vl)","Greek salad (g,k,v,vl)","Banana quark (g,k,l)"],["Meat stew with basil ([S],l)"," (l)","Soya balls in chili-tomato sauce ([S],g,k,l,m,pä,so,v,ve)","Mackerel salad ([S],g,l,m)","Leek-potato purée soup (g,k,l)"],["Meatballs with gravy (l,so,v)","Baked fish with spinach (l)","Sweet potato-bean sauté ([S],g,k,l,m,v,ve)"," (g,k,l,v)"],["Herring, dill-sour cream sauce ([S],l)","Tofu and potato casserole ([S],k,l,m,so,v,ve)","Chicken, chili and coconut ([S],g,l,m,se,so,v)","Salad with smoked fish and asparagus ([S],g,l,m)","Goat cheese soupfruit (g,k,l,v)"],["Minced meat sauce, grated cheese ([S],l,v)","Vegetablesteaks, bean salsa ([S],g,k,l,m,se,v,ve)"," ([S],g,l,m)"," "]]}},{"name":"Unicafe Korona","address":"Viikinkaari 11, Helsinki","campus":"Viikki","open":"Mon-Fri 11:00-14:00","url":{"fi":"http://www.hyyravintolat.fi/rss/fin/19/","en":"http://www.hyyravintolat.fi/rss/eng/19/"},"location":{"lat":60.2271911,"lng":25.0123344},"meals":{"fi":[],"en":[]}},{"name":"Unicafe Viikuna","address":"Agnes Sjöbergin katu 2, Helsinki","campus":"Viikki","open":"Mon-Fri 10:30-14:30","url":{"fi":"http://www.hyyravintolat.fi/rss/fin/21/","en":"http://www.hyyravintolat.fi/rss/eng/21/"},"location":{"lat":60.229297,"lng":25.0218129},"meals":{"fi":[["RAVINTOLA SULJETTU 20.6-4.8.2013.TOIVOTAMME ASIAKKAILLEMME AURINKOISTA KESÄÄ! AVAAMME JÄLLEEN 5.8.2013 KLO 08.00. "]],"en":[["RESTAURANT IS CLOSED 20.6-4.8.2013. WE WISH ALL OUR CUSTOMERS A SUNNY SUMMER! WE ARE OPEN AGAIN 5.8.2013 CLOCK 08.00. "]]}},{"name":"Tähkä","address":"Koetilantie 7, Helsinki","campus":"Viikki","open":"Mon-Thu 10:30-13:30, Fri 10:30-13:00","url":{"fi":"http://www.amica.fi/tahka"},"location":{"lat":60.2230593,"lng":25.0206768},"meals":{"fi":[["Herkkusieni-pekonikastiketta (G,VL,*),  Luomu täysjyväspaghetti (L,M,*)","Lahnapyörykät (VL),  Ruohosipulikastiketta (VL,*),  tilliperunoita","Sieni-pinaattitäytteiset paprikat (G,L*),  Täysjyväohra (L,M,*)","Parsakaalisosekeitto (G,VL,*)","Mangorahkaa (G, L)"],["Broileria ananas-currykastikkeessa (G,L,M,*),  Tummaa riisiä (L,M,*)","Riistakäristys(G,L, M), Perunasosetta (*, G, VL)","Jauhelihakeitto (G,L,M,*)","Juusto-maissitäytteiset ohukaiset, Jogurtti-ananaskastiketta (*, L, G)","Mustaherukkakiisseli (L,M,G)"],[" Tomaattista jauheliha-paprikakastiketta( ,L,M,*), perunoita","Mantelikala (M, L), Perunasosetta (*, G, VL)","Smetanaista kaalivuokaa (G,L)","Kesäkeitto (VL,*)","Sitruunakiisseli (G, L,M)"],["Keitetyt nakit (G,L,M),  Sinappikastike (G,VL)","Broileri-kasvisvarras (G,L,M),  basmatriisiä (G,L,M),  hapanimeläkastiketta (G,L,M)","KylmäsavuLohikeitto (*, G)","Leipäjuusto-sienipaella (G,VL,*),  jogurtti-ananaskastiketta (G,L,*)","Ohukaisia,Mansikkahilloa"],["Smetanaista kalkkuna-pastavuokaa (L,*)","Stroganoofia (VL),  Täysjyvävehnää (L,M)","Chili con vege (G,L,M,*),  tummaa riisiä ( G,L,M,*)","Marjasalaatti (G,L,M),  kinuskikermavaahtoa (G)"]],"en":[["Mushroom-Bacon sauce (G, VL, *), organic täysjyväspaghetti (L), (M, *)","Bream dumplings (VL), chives sauce (VL, *), dill potatoes","Fungal pinaattitäytteiset peppers (G, L *), Täysjyväohra (L), (M, *)","Broccoli Puree Soup (G, VL, *)","Mango Curd (G, L)"],["Chicken pineapple curry sauce (G, L, M, *), brown rice (L), (M, *)","Game Soup (G, L, M), Potato Puree (*, G, VL)","Minced Meat Soup (G, L, M, *)","Cheese-maissitäytteiset pancakes, yogurt-pineapple sauce (L, G)","Mustaherukkakiisseli (L), (M, G)"],[" Tomaattista minced meat-pepper sauce (L, M, *), potatoes","Almond Fish (M, L), Potato Puree (*, G, VL)","Smetanaista cabbage vuokaa (G, L)","Summer Soup (VL, *)","Lemon Pudding (G, L, M)"],["Cooked sausages (G, L, M), mustard sauce (G, VL)","Chicken-vegetable skewer (G, L, M), basmatriisiä (G), (L), (M), hapanimeläkastiketta (G, L, M)","KylmäsavuLohikeitto (*, G)","Bread cheese mushroom paella (G, VL, *), yogurt-pineapple sauce (G), (L), (*)","Crepes, Strawberry Jam"],["Smetanaista Turkey-pasta vuokaa (L *)","Stroganoofia (VL), Whole Wheat (L, M)","Chili con vege (G, L, M, *), brown rice (G, L, M, *)","Berry salad (G), (L), (M), caramel whipped cream (G)"]]}},{"name":"Ladonlukko","address":"Latokartanonkaari 9 A, Helsinki","campus":"Viikki","open":"Mon-Fri 10:30-14:30","url":{"fi":"http://www.sodexo.fi/ravintolaladonlukko"},"location":{"lat":60.2290679,"lng":25.0185889},"meals":{"fi":[["Kalapuikot, tilli-kermaviilikastike, peruna (L)","Ratatouille, keitetty riisi (G, M)","Tonnikalasalaatti (G, M)"],["Broileri-herkkusienipata, täysjyväriisi (G, VL)","Kasvis-papukroketit, jogurttikastike, keitetty riisi (G, VL)","Leipäjuustosalaatti (G, VL)"],["Liha-makaronilaatikko (VL)","Intialainen linssi-kasvishöystö, keitetty riisi (G, M)","Minilihapullasalaatti (G, M)"],["Chili-suklaa broileri, jogurttikastike, riisi (G, VL)","Kasvismoussaka (G, VL)","Broilerisalaatti (G, M)"],["Uuniperuna katkaraputäytteellä (G, L)","Soija-kasvislasagnette (VL)","Parmesansalaatti (G)"]],"en":[["Fish fingers, dill-sourcreamsauce, potatoes (L)","Ratatouille, boiled rice (G, M)","Tunafish salad (G, M)"],["Chicken and mushroom stew, whole grain rice (G, VL)","Vegetable and bean croquettes, yogurt sauce, boiled rice (G, VL)","Baked cheese salad (G, VL)"],["Macaroni casserole with minced meat (VL)","Indian style lentil and vegetable raqout, boiled rice (G, M)","Salad with mini meatballs (G, M)"],["Chicken with chili and chocolate, yogurtsauce, rice (G, VL)","Vegetable moussaka (G, VL)","Chickensalad (G, M)"],["Baked potato with shrimp topping (G, L)","Soy and vegetable lasagnette (VL)","Parmesan salad (G)"]]}}]